{
  "lastUpdated": "2026-05-19T02:55:48.340Z",
  "providers": {
    "Ashley Grout, NP": {
      "providerType": "NP",
      "licenses": [
        {
          "state": "FL",
          "stateFullName": "Florida",
          "licenseNumber": "RN9361181",
          "licenseType": "RN",
          "status": "Active",
          "expirationDate": null,
          "issuedDate": null,
          "verificationSource": "FL DOH MQA",
          "lastVerified": "2026-05-19T02:45:38.169Z",
          "disciplineActions": false
        },
        {
          "state": "FL",
          "stateFullName": "Florida",
          "licenseNumber": "APRN9361181",
          "licenseType": "RN",
          "status": "Active",
          "expirationDate": null,
          "issuedDate": null,
          "verificationSource": "FL DOH MQA",
          "lastVerified": "2026-05-19T02:45:38.169Z",
          "disciplineActions": false
        },
        {
          "state": "FL",
          "stateFullName": "Florida",
          "licenseNumber": "PTA27860",
          "licenseType": "RN",
          "status": "Active",
          "expirationDate": null,
          "issuedDate": null,
          "verificationSource": "FL DOH MQA",
          "lastVerified": "2026-05-19T02:45:38.169Z",
          "disciplineActions": false
        }
      ],
      "statesSearched": 2,
      "statesWithLicense": 3,
      "lastFullScan": "2026-05-19T02:45:49.057Z"
    },
    "Bill Carbonneau, NP": {
      "providerType": "NP",
      "licenses": [],
      "statesSearched": 2,
      "statesWithLicense": 0,
      "lastFullScan": "2026-05-19T02:46:08.607Z"
    },
    "Bryana Anderson, NP": {
      "providerType": "NP",
      "licenses": [],
      "statesSearched": 2,
      "statesWithLicense": 0,
      "lastFullScan": "2026-05-19T02:46:28.114Z"
    },
    "Bryce Amos, NP": {
      "providerType": "NP",
      "licenses": [],
      "statesSearched": 2,
      "statesWithLicense": 0,
      "lastFullScan": "2026-05-19T02:46:47.739Z"
    },
    "Hilary Morgan, RN": {
      "providerType": "RN",
      "licenses": [
        {
          "state": "FL",
          "stateFullName": "Florida",
          "licenseNumber": "RN1098682",
          "licenseType": "RN",
          "status": "Active",
          "expirationDate": null,
          "issuedDate": null,
          "verificationSource": "FL DOH MQA",
          "lastVerified": "2026-05-19T02:47:34.922Z",
          "disciplineActions": false
        },
        {
          "state": "FL",
          "stateFullName": "Florida",
          "licenseNumber": "APRN1098682",
          "licenseType": "RN",
          "status": "Active",
          "expirationDate": null,
          "issuedDate": null,
          "verificationSource": "FL DOH MQA",
          "lastVerified": "2026-05-19T02:47:34.922Z",
          "disciplineActions": false
        }
      ],
      "statesSearched": 2,
      "statesWithLicense": 2,
      "lastFullScan": "2026-05-19T02:47:46.571Z"
    },
    "Jacquelyn Sexton, NP": {
      "providerType": "NP",
      "licenses": [],
      "statesSearched": 2,
      "statesWithLicense": 0,
      "lastFullScan": "2026-03-01T22:51:55.801Z"
    },
    "Lindsay Burden, NP": {
      "providerType": "NP",
      "licenses": [
        {
          "state": "FL",
          "stateFullName": "Florida",
          "licenseNumber": "RN9337451",
          "licenseType": "RN",
          "status": "Active",
          "expirationDate": null,
          "issuedDate": null,
          "verificationSource": "FL DOH MQA",
          "lastVerified": "2026-05-19T02:47:55.088Z",
          "disciplineActions": false
        },
        {
          "state": "FL",
          "stateFullName": "Florida",
          "licenseNumber": "APRN9337451",
          "licenseType": "RN",
          "status": "Active",
          "expirationDate": null,
          "issuedDate": null,
          "verificationSource": "FL DOH MQA",
          "lastVerified": "2026-05-19T02:47:55.088Z",
          "disciplineActions": false
        },
        {
          "state": "NH",
          "stateFullName": "New Hampshire",
          "licenseNumber": "112115",
          "licenseType": "APRN",
          "status": "Active",
          "expirationDate": null,
          "issuedDate": null,
          "verificationSource": "New Hampshire Board",
          "lastVerified": "2026-05-19T02:48:04.660Z",
          "disciplineActions": false
        }
      ],
      "statesSearched": 2,
      "statesWithLicense": 3,
      "lastFullScan": "2026-05-19T02:48:06.180Z"
    },
    "Liz Gloor, NP": {
      "providerType": "NP",
      "licenses": [],
      "statesSearched": 2,
      "statesWithLicense": 0,
      "lastFullScan": "2026-05-19T02:48:26.421Z"
    },
    "Mackinzie Johnson, RN": {
      "providerType": "RN",
      "licenses": [],
      "statesSearched": 2,
      "statesWithLicense": 0,
      "lastFullScan": "2026-03-02T15:23:46.676Z"
    },
    "Martin Van Dongen, NP": {
      "providerType": "NP",
      "licenses": [],
      "statesSearched": 2,
      "statesWithLicense": 0,
      "lastFullScan": "2026-03-02T15:24:08.369Z"
    },
    "Priya Chaudhari, NP": {
      "providerType": "NP",
      "licenses": [],
      "statesSearched": 2,
      "statesWithLicense": 0,
      "lastFullScan": "2026-05-19T02:48:45.687Z"
    },
    "Rachel Razi, NP": {
      "providerType": "NP",
      "licenses": [],
      "statesSearched": 2,
      "statesWithLicense": 0,
      "lastFullScan": "2026-05-19T02:49:04.460Z"
    },
    "Summer Denny, NP": {
      "providerType": "NP",
      "licenses": [
        {
          "state": "FL",
          "stateFullName": "Florida",
          "licenseNumber": "RN9360075",
          "licenseType": "RN",
          "status": "Inactive",
          "expirationDate": null,
          "issuedDate": null,
          "verificationSource": "FL DOH MQA",
          "lastVerified": "2026-05-19T02:49:12.820Z",
          "disciplineActions": false
        },
        {
          "state": "FL",
          "stateFullName": "Florida",
          "licenseNumber": "APRN11031615",
          "licenseType": "RN",
          "status": "Active",
          "expirationDate": null,
          "issuedDate": null,
          "verificationSource": "FL DOH MQA",
          "lastVerified": "2026-05-19T02:49:12.820Z",
          "disciplineActions": false
        }
      ],
      "statesSearched": 2,
      "statesWithLicense": 2,
      "lastFullScan": "2026-05-19T02:49:23.418Z"
    },
    "Terray Humphrey, NP": {
      "providerType": "NP",
      "licenses": [],
      "statesSearched": 2,
      "statesWithLicense": 0,
      "lastFullScan": "2026-05-19T02:49:42.566Z"
    },
    "Tim Mack, NP": {
      "providerType": "NP",
      "licenses": [
        {
          "state": "FL",
          "stateFullName": "Florida",
          "licenseNumber": "RPT73460",
          "licenseType": "RN",
          "status": "Active",
          "expirationDate": null,
          "issuedDate": null,
          "verificationSource": "FL DOH MQA",
          "lastVerified": "2026-05-19T02:49:51.005Z",
          "disciplineActions": false
        },
        {
          "state": "FL",
          "stateFullName": "Florida",
          "licenseNumber": "SA18295",
          "licenseType": "RN",
          "status": "Inactive",
          "expirationDate": null,
          "issuedDate": null,
          "verificationSource": "FL DOH MQA",
          "lastVerified": "2026-05-19T02:49:51.005Z",
          "disciplineActions": false
        },
        {
          "state": "FL",
          "stateFullName": "Florida",
          "licenseNumber": null,
          "licenseType": "RN",
          "status": "Active",
          "expirationDate": null,
          "issuedDate": null,
          "verificationSource": "FL DOH MQA",
          "lastVerified": "2026-05-19T02:49:51.005Z",
          "disciplineActions": false
        },
        {
          "state": "FL",
          "stateFullName": "Florida",
          "licenseNumber": null,
          "licenseType": "RN",
          "status": "Inactive",
          "expirationDate": null,
          "issuedDate": null,
          "verificationSource": "FL DOH MQA",
          "lastVerified": "2026-05-19T02:49:51.005Z",
          "disciplineActions": false
        },
        {
          "state": "NH",
          "stateFullName": "New Hampshire",
          "licenseNumber": "117469",
          "licenseType": "APRN",
          "status": "Active",
          "expirationDate": null,
          "issuedDate": null,
          "verificationSource": "New Hampshire Board",
          "lastVerified": "2026-05-19T02:50:00.444Z",
          "disciplineActions": false
        }
      ],
      "statesSearched": 2,
      "statesWithLicense": 5,
      "lastFullScan": "2026-05-19T02:50:01.956Z"
    },
    "Vivien Lee, NP": {
      "providerType": "NP",
      "licenses": [],
      "statesSearched": 2,
      "statesWithLicense": 0,
      "lastFullScan": "2026-05-19T02:50:40.212Z"
    },
    "Victor Lopez, NP": {
      "providerType": "NP",
      "licenses": [
        {
          "state": "FL",
          "stateFullName": "Florida",
          "licenseNumber": "RPT49689",
          "licenseType": "RN",
          "status": "Inactive",
          "expirationDate": null,
          "issuedDate": null,
          "verificationSource": "FL DOH MQA",
          "lastVerified": "2026-05-19T02:50:48.640Z",
          "disciplineActions": false
        },
        {
          "state": "FL",
          "stateFullName": "Florida",
          "licenseNumber": "RPT95405",
          "licenseType": "RN",
          "status": "Active",
          "expirationDate": null,
          "issuedDate": null,
          "verificationSource": "FL DOH MQA",
          "lastVerified": "2026-05-19T02:50:48.640Z",
          "disciplineActions": false
        },
        {
          "state": "FL",
          "stateFullName": "Florida",
          "licenseNumber": null,
          "licenseType": "RN",
          "status": "Active",
          "expirationDate": null,
          "issuedDate": null,
          "verificationSource": "FL DOH MQA",
          "lastVerified": "2026-05-19T02:50:48.640Z",
          "disciplineActions": false
        },
        {
          "state": "FL",
          "stateFullName": "Florida",
          "licenseNumber": "CNA233200",
          "licenseType": "RN",
          "status": "Inactive",
          "expirationDate": null,
          "issuedDate": null,
          "verificationSource": "FL DOH MQA",
          "lastVerified": "2026-05-19T02:50:48.640Z",
          "disciplineActions": false
        },
        {
          "state": "FL",
          "stateFullName": "Florida",
          "licenseNumber": "EMT586994",
          "licenseType": "RN",
          "status": "Active",
          "expirationDate": null,
          "issuedDate": null,
          "verificationSource": "FL DOH MQA",
          "lastVerified": "2026-05-19T02:50:48.640Z",
          "disciplineActions": false
        },
        {
          "state": "FL",
          "stateFullName": "Florida",
          "licenseNumber": "CRT85005",
          "licenseType": "RN",
          "status": "Active",
          "expirationDate": null,
          "issuedDate": null,
          "verificationSource": "FL DOH MQA",
          "lastVerified": "2026-05-19T02:50:48.640Z",
          "disciplineActions": false
        },
        {
          "state": "FL",
          "stateFullName": "Florida",
          "licenseNumber": "APRN9221773",
          "licenseType": "RN",
          "status": "Active",
          "expirationDate": null,
          "issuedDate": null,
          "verificationSource": "FL DOH MQA",
          "lastVerified": "2026-05-19T02:50:48.640Z",
          "disciplineActions": false
        },
        {
          "state": "FL",
          "stateFullName": "Florida",
          "licenseNumber": "RN9221773",
          "licenseType": "RN",
          "status": "Active",
          "expirationDate": null,
          "issuedDate": null,
          "verificationSource": "FL DOH MQA",
          "lastVerified": "2026-05-19T02:50:48.640Z",
          "disciplineActions": false
        },
        {
          "state": "FL",
          "stateFullName": "Florida",
          "licenseNumber": "MA56435",
          "licenseType": "RN",
          "status": "Unknown",
          "expirationDate": null,
          "issuedDate": null,
          "verificationSource": "FL DOH MQA",
          "lastVerified": "2026-05-19T02:50:48.640Z",
          "disciplineActions": false
        },
        {
          "state": "FL",
          "stateFullName": "Florida",
          "licenseNumber": null,
          "licenseType": "RN",
          "status": "Active",
          "expirationDate": null,
          "issuedDate": null,
          "verificationSource": "FL DOH MQA",
          "lastVerified": "2026-05-19T02:50:48.640Z",
          "disciplineActions": false
        },
        {
          "state": "FL",
          "stateFullName": "Florida",
          "licenseNumber": "RN9651384",
          "licenseType": "RN",
          "status": "Active",
          "expirationDate": null,
          "issuedDate": null,
          "verificationSource": "FL DOH MQA",
          "lastVerified": "2026-05-19T02:50:48.640Z",
          "disciplineActions": false
        },
        {
          "state": "FL",
          "stateFullName": "Florida",
          "licenseNumber": "CNA185762",
          "licenseType": "RN",
          "status": "Unknown",
          "expirationDate": null,
          "issuedDate": null,
          "verificationSource": "FL DOH MQA",
          "lastVerified": "2026-05-19T02:50:48.640Z",
          "disciplineActions": false
        },
        {
          "state": "FL",
          "stateFullName": "Florida",
          "licenseNumber": "DH20421",
          "licenseType": "RN",
          "status": "Inactive",
          "expirationDate": null,
          "issuedDate": null,
          "verificationSource": "FL DOH MQA",
          "lastVerified": "2026-05-19T02:50:48.640Z",
          "disciplineActions": false
        },
        {
          "state": "FL",
          "stateFullName": "Florida",
          "licenseNumber": "DR127918",
          "licenseType": "RN",
          "status": "Active",
          "expirationDate": null,
          "issuedDate": null,
          "verificationSource": "FL DOH MQA",
          "lastVerified": "2026-05-19T02:50:48.640Z",
          "disciplineActions": false
        },
        {
          "state": "FL",
          "stateFullName": "Florida",
          "licenseNumber": null,
          "licenseType": "RN",
          "status": "Inactive",
          "expirationDate": null,
          "issuedDate": null,
          "verificationSource": "FL DOH MQA",
          "lastVerified": "2026-05-19T02:50:48.640Z",
          "disciplineActions": false
        },
        {
          "state": "FL",
          "stateFullName": "Florida",
          "licenseNumber": "RN9465082",
          "licenseType": "RN",
          "status": "Active",
          "expirationDate": null,
          "issuedDate": null,
          "verificationSource": "FL DOH MQA",
          "lastVerified": "2026-05-19T02:50:48.640Z",
          "disciplineActions": false
        },
        {
          "state": "FL",
          "stateFullName": "Florida",
          "licenseNumber": "TC50541",
          "licenseType": "RN",
          "status": "Inactive",
          "expirationDate": null,
          "issuedDate": null,
          "verificationSource": "FL DOH MQA",
          "lastVerified": "2026-05-19T02:50:48.640Z",
          "disciplineActions": false
        },
        {
          "state": "FL",
          "stateFullName": "Florida",
          "licenseNumber": null,
          "licenseType": "RN",
          "status": "Inactive",
          "expirationDate": null,
          "issuedDate": null,
          "verificationSource": "FL DOH MQA",
          "lastVerified": "2026-05-19T02:50:48.640Z",
          "disciplineActions": false
        },
        {
          "state": "FL",
          "stateFullName": "Florida",
          "licenseNumber": null,
          "licenseType": "RN",
          "status": "Inactive",
          "expirationDate": null,
          "issuedDate": null,
          "verificationSource": "FL DOH MQA",
          "lastVerified": "2026-05-19T02:50:48.640Z",
          "disciplineActions": false
        },
        {
          "state": "FL",
          "stateFullName": "Florida",
          "licenseNumber": "TRN27500",
          "licenseType": "RN",
          "status": "Inactive",
          "expirationDate": null,
          "issuedDate": null,
          "verificationSource": "FL DOH MQA",
          "lastVerified": "2026-05-19T02:50:48.640Z",
          "disciplineActions": false
        }
      ],
      "statesSearched": 2,
      "statesWithLicense": 20,
      "lastFullScan": "2026-05-19T02:50:59.127Z"
    },
    "Camryn Burden, RN": {
      "providerType": "RN",
      "licenses": [
        {
          "state": "FL",
          "stateFullName": "Florida",
          "licenseNumber": "CNA376135",
          "licenseType": "RN",
          "status": "Active",
          "expirationDate": null,
          "issuedDate": null,
          "verificationSource": "FL DOH MQA",
          "lastVerified": "2026-05-19T02:51:07.556Z",
          "disciplineActions": false
        },
        {
          "state": "FL",
          "stateFullName": "Florida",
          "licenseNumber": "RN9660348",
          "licenseType": "RN",
          "status": "Active",
          "expirationDate": null,
          "issuedDate": null,
          "verificationSource": "FL DOH MQA",
          "lastVerified": "2026-05-19T02:51:07.556Z",
          "disciplineActions": false
        }
      ],
      "statesSearched": 2,
      "statesWithLicense": 2,
      "lastFullScan": "2026-05-19T02:51:18.033Z"
    },
    "Alexis Foster-Horton, NP": {
      "providerType": "NP",
      "licenses": [],
      "statesSearched": 2,
      "statesWithLicense": 0,
      "lastFullScan": "2026-05-19T02:51:37.659Z"
    },
    "Megan Ryan-Riffle, NP": {
      "providerType": "NP",
      "licenses": [],
      "statesSearched": 2,
      "statesWithLicense": 0,
      "lastFullScan": "2026-05-19T02:51:56.748Z"
    },
    "Michele Foster, NP": {
      "providerType": "NP",
      "licenses": [
        {
          "state": "FL",
          "stateFullName": "Florida",
          "licenseNumber": "BMO103851",
          "licenseType": "RN",
          "status": "Active",
          "expirationDate": null,
          "issuedDate": null,
          "verificationSource": "FL DOH MQA",
          "lastVerified": "2026-05-19T02:52:05.286Z",
          "disciplineActions": false
        },
        {
          "state": "FL",
          "stateFullName": "Florida",
          "licenseNumber": "CRT35278",
          "licenseType": "RN",
          "status": "Active",
          "expirationDate": null,
          "issuedDate": null,
          "verificationSource": "FL DOH MQA",
          "lastVerified": "2026-05-19T02:52:05.286Z",
          "disciplineActions": false
        },
        {
          "state": "FL",
          "stateFullName": "Florida",
          "licenseNumber": "RN1618492",
          "licenseType": "RN",
          "status": "Inactive",
          "expirationDate": null,
          "issuedDate": null,
          "verificationSource": "FL DOH MQA",
          "lastVerified": "2026-05-19T02:52:05.286Z",
          "disciplineActions": false
        },
        {
          "state": "FL",
          "stateFullName": "Florida",
          "licenseNumber": "RN9618492",
          "licenseType": "RN",
          "status": "Active",
          "expirationDate": null,
          "issuedDate": null,
          "verificationSource": "FL DOH MQA",
          "lastVerified": "2026-05-19T02:52:05.286Z",
          "disciplineActions": false
        }
      ],
      "statesSearched": 2,
      "statesWithLicense": 4,
      "lastFullScan": "2026-05-19T02:52:15.755Z"
    },
    "Danielle Board, NP": {
      "providerType": "NP",
      "licenses": [],
      "statesSearched": 2,
      "statesWithLicense": 0,
      "lastFullScan": "2026-05-19T02:52:34.678Z"
    },
    "DeAnna Maher, NP": {
      "providerType": "NP",
      "licenses": [],
      "statesSearched": 2,
      "statesWithLicense": 0,
      "lastFullScan": "2026-05-19T02:52:54.464Z"
    },
    "Skye Sauls, NP": {
      "providerType": "NP",
      "licenses": [
        {
          "state": "FL",
          "stateFullName": "Florida",
          "licenseNumber": "CNA251481",
          "licenseType": "RN",
          "status": "Inactive",
          "expirationDate": null,
          "issuedDate": null,
          "verificationSource": "FL DOH MQA",
          "lastVerified": "2026-03-02T15:29:10.685Z",
          "disciplineActions": false
        },
        {
          "state": "FL",
          "stateFullName": "Florida",
          "licenseNumber": "RN9398137",
          "licenseType": "RN",
          "status": "Active",
          "expirationDate": null,
          "issuedDate": null,
          "verificationSource": "FL DOH MQA",
          "lastVerified": "2026-03-02T15:29:10.685Z",
          "disciplineActions": false
        },
        {
          "state": "FL",
          "stateFullName": "Florida",
          "licenseNumber": "APRN11025749",
          "licenseType": "RN",
          "status": "Active",
          "expirationDate": null,
          "issuedDate": null,
          "verificationSource": "FL DOH MQA",
          "lastVerified": "2026-03-02T15:29:10.685Z",
          "disciplineActions": false
        }
      ],
      "statesSearched": 2,
      "statesWithLicense": 3,
      "lastFullScan": "2026-03-02T15:29:21.512Z"
    },
    "Brooklyn Kimble, RN": {
      "providerType": "RN",
      "licenses": [],
      "statesSearched": 2,
      "statesWithLicense": 0,
      "lastFullScan": "2026-05-19T02:53:33.142Z"
    },
    "Daniel Fis, RN": {
      "providerType": "RN",
      "licenses": [
        {
          "state": "FL",
          "stateFullName": "Florida",
          "licenseNumber": null,
          "licenseType": "RN",
          "status": "Inactive",
          "expirationDate": null,
          "issuedDate": null,
          "verificationSource": "FL DOH MQA",
          "lastVerified": "2026-05-19T02:53:41.785Z",
          "disciplineActions": false
        },
        {
          "state": "FL",
          "stateFullName": "Florida",
          "licenseNumber": "PTA20165",
          "licenseType": "RN",
          "status": "Inactive",
          "expirationDate": null,
          "issuedDate": null,
          "verificationSource": "FL DOH MQA",
          "lastVerified": "2026-05-19T02:53:41.785Z",
          "disciplineActions": false
        },
        {
          "state": "FL",
          "stateFullName": "Florida",
          "licenseNumber": "PTA34374",
          "licenseType": "RN",
          "status": "Active",
          "expirationDate": null,
          "issuedDate": null,
          "verificationSource": "FL DOH MQA",
          "lastVerified": "2026-05-19T02:53:41.785Z",
          "disciplineActions": false
        },
        {
          "state": "FL",
          "stateFullName": "Florida",
          "licenseNumber": "EMT506665",
          "licenseType": "RN",
          "status": "Inactive",
          "expirationDate": null,
          "issuedDate": null,
          "verificationSource": "FL DOH MQA",
          "lastVerified": "2026-05-19T02:53:41.785Z",
          "disciplineActions": false
        },
        {
          "state": "FL",
          "stateFullName": "Florida",
          "licenseNumber": "PMD517352",
          "licenseType": "RN",
          "status": "Active",
          "expirationDate": null,
          "issuedDate": null,
          "verificationSource": "FL DOH MQA",
          "lastVerified": "2026-05-19T02:53:41.785Z",
          "disciplineActions": false
        },
        {
          "state": "FL",
          "stateFullName": "Florida",
          "licenseNumber": "ME15864",
          "licenseType": "MD",
          "status": "Inactive",
          "expirationDate": null,
          "issuedDate": null,
          "verificationSource": "FL DOH MQA",
          "lastVerified": "2026-05-19T02:53:41.785Z",
          "disciplineActions": false
        },
        {
          "state": "FL",
          "stateFullName": "Florida",
          "licenseNumber": "ME17917",
          "licenseType": "MD",
          "status": "Inactive",
          "expirationDate": null,
          "issuedDate": null,
          "verificationSource": "FL DOH MQA",
          "lastVerified": "2026-05-19T02:53:41.785Z",
          "disciplineActions": false
        },
        {
          "state": "FL",
          "stateFullName": "Florida",
          "licenseNumber": "OS16218",
          "licenseType": "RN",
          "status": "Active",
          "expirationDate": null,
          "issuedDate": null,
          "verificationSource": "FL DOH MQA",
          "lastVerified": "2026-05-19T02:53:41.785Z",
          "disciplineActions": false
        },
        {
          "state": "FL",
          "stateFullName": "Florida",
          "licenseNumber": "CNA221910",
          "licenseType": "RN",
          "status": "Inactive",
          "expirationDate": null,
          "issuedDate": null,
          "verificationSource": "FL DOH MQA",
          "lastVerified": "2026-05-19T02:53:41.785Z",
          "disciplineActions": false
        },
        {
          "state": "FL",
          "stateFullName": "Florida",
          "licenseNumber": "RN9373081",
          "licenseType": "RN",
          "status": "Inactive",
          "expirationDate": null,
          "issuedDate": null,
          "verificationSource": "FL DOH MQA",
          "lastVerified": "2026-05-19T02:53:41.785Z",
          "disciplineActions": false
        },
        {
          "state": "FL",
          "stateFullName": "Florida",
          "licenseNumber": "RPT18925",
          "licenseType": "RN",
          "status": "Inactive",
          "expirationDate": null,
          "issuedDate": null,
          "verificationSource": "FL DOH MQA",
          "lastVerified": "2026-05-19T02:53:41.785Z",
          "disciplineActions": false
        },
        {
          "state": "FL",
          "stateFullName": "Florida",
          "licenseNumber": null,
          "licenseType": "RN",
          "status": "Active",
          "expirationDate": null,
          "issuedDate": null,
          "verificationSource": "FL DOH MQA",
          "lastVerified": "2026-05-19T02:53:41.785Z",
          "disciplineActions": false
        },
        {
          "state": "FL",
          "stateFullName": "Florida",
          "licenseNumber": null,
          "licenseType": "RN",
          "status": "Inactive",
          "expirationDate": null,
          "issuedDate": null,
          "verificationSource": "FL DOH MQA",
          "lastVerified": "2026-05-19T02:53:41.785Z",
          "disciplineActions": false
        },
        {
          "state": "FL",
          "stateFullName": "Florida",
          "licenseNumber": null,
          "licenseType": "RN",
          "status": "Inactive",
          "expirationDate": null,
          "issuedDate": null,
          "verificationSource": "FL DOH MQA",
          "lastVerified": "2026-05-19T02:53:41.785Z",
          "disciplineActions": false
        },
        {
          "state": "FL",
          "stateFullName": "Florida",
          "licenseNumber": "EMT574316",
          "licenseType": "RN",
          "status": "Inactive",
          "expirationDate": null,
          "issuedDate": null,
          "verificationSource": "FL DOH MQA",
          "lastVerified": "2026-05-19T02:53:41.785Z",
          "disciplineActions": false
        },
        {
          "state": "FL",
          "stateFullName": "Florida",
          "licenseNumber": null,
          "licenseType": "RN",
          "status": "Inactive",
          "expirationDate": null,
          "issuedDate": null,
          "verificationSource": "FL DOH MQA",
          "lastVerified": "2026-05-19T02:53:41.785Z",
          "disciplineActions": false
        },
        {
          "state": "FL",
          "stateFullName": "Florida",
          "licenseNumber": "RN9285776",
          "licenseType": "RN",
          "status": "Inactive",
          "expirationDate": null,
          "issuedDate": null,
          "verificationSource": "FL DOH MQA",
          "lastVerified": "2026-05-19T02:53:41.785Z",
          "disciplineActions": false
        },
        {
          "state": "FL",
          "stateFullName": "Florida",
          "licenseNumber": "MH13042",
          "licenseType": "RN",
          "status": "Active",
          "expirationDate": null,
          "issuedDate": null,
          "verificationSource": "FL DOH MQA",
          "lastVerified": "2026-05-19T02:53:41.785Z",
          "disciplineActions": false
        },
        {
          "state": "FL",
          "stateFullName": "Florida",
          "licenseNumber": null,
          "licenseType": "RN",
          "status": "Inactive",
          "expirationDate": null,
          "issuedDate": null,
          "verificationSource": "FL DOH MQA",
          "lastVerified": "2026-05-19T02:53:41.785Z",
          "disciplineActions": false
        },
        {
          "state": "FL",
          "stateFullName": "Florida",
          "licenseNumber": "ME162847",
          "licenseType": "MD",
          "status": "Active",
          "expirationDate": null,
          "issuedDate": null,
          "verificationSource": "FL DOH MQA",
          "lastVerified": "2026-05-19T02:53:41.785Z",
          "disciplineActions": false
        },
        {
          "state": "NH",
          "stateFullName": "New Hampshire",
          "licenseNumber": "18331",
          "licenseType": "APRN",
          "status": "Active",
          "expirationDate": null,
          "issuedDate": null,
          "verificationSource": "New Hampshire Board",
          "lastVerified": "2026-05-19T02:53:51.011Z",
          "disciplineActions": false
        }
      ],
      "statesSearched": 2,
      "statesWithLicense": 21,
      "lastFullScan": "2026-05-19T02:53:52.524Z"
    },
    "Bryce Hanley, RN": {
      "providerType": "RN",
      "licenses": [],
      "statesSearched": 2,
      "statesWithLicense": 0,
      "lastFullScan": "2026-05-19T02:54:11.739Z"
    },
    "Shelby Bailey, RN": {
      "providerType": "RN",
      "licenses": [
        {
          "state": "NH",
          "stateFullName": "New Hampshire",
          "licenseNumber": "052423",
          "licenseType": "APRN",
          "status": "Active",
          "expirationDate": null,
          "issuedDate": null,
          "verificationSource": "New Hampshire Board",
          "lastVerified": "2026-05-19T02:54:29.129Z",
          "disciplineActions": false
        }
      ],
      "statesSearched": 2,
      "statesWithLicense": 1,
      "lastFullScan": "2026-05-19T02:54:30.654Z"
    },
    "Brittany Alexander, RN": {
      "providerType": "RN",
      "licenses": [
        {
          "state": "FL",
          "stateFullName": "Florida",
          "licenseNumber": "CNA324455",
          "licenseType": "RN",
          "status": "Active",
          "expirationDate": null,
          "issuedDate": null,
          "verificationSource": "FL DOH MQA",
          "lastVerified": "2026-05-19T02:54:39.070Z",
          "disciplineActions": false
        },
        {
          "state": "FL",
          "stateFullName": "Florida",
          "licenseNumber": "CNA290739",
          "licenseType": "RN",
          "status": "Inactive",
          "expirationDate": null,
          "issuedDate": null,
          "verificationSource": "FL DOH MQA",
          "lastVerified": "2026-05-19T02:54:39.070Z",
          "disciplineActions": false
        },
        {
          "state": "FL",
          "stateFullName": "Florida",
          "licenseNumber": "CNA367063",
          "licenseType": "RN",
          "status": "Inactive",
          "expirationDate": null,
          "issuedDate": null,
          "verificationSource": "FL DOH MQA",
          "lastVerified": "2026-05-19T02:54:39.070Z",
          "disciplineActions": false
        },
        {
          "state": "FL",
          "stateFullName": "Florida",
          "licenseNumber": "CNA188754",
          "licenseType": "RN",
          "status": "Inactive",
          "expirationDate": null,
          "issuedDate": null,
          "verificationSource": "FL DOH MQA",
          "lastVerified": "2026-05-19T02:54:39.070Z",
          "disciplineActions": false
        },
        {
          "state": "FL",
          "stateFullName": "Florida",
          "licenseNumber": "MH15782",
          "licenseType": "RN",
          "status": "Active",
          "expirationDate": null,
          "issuedDate": null,
          "verificationSource": "FL DOH MQA",
          "lastVerified": "2026-05-19T02:54:39.070Z",
          "disciplineActions": false
        },
        {
          "state": "FL",
          "stateFullName": "Florida",
          "licenseNumber": "IMH13566",
          "licenseType": "RN",
          "status": "Inactive",
          "expirationDate": null,
          "issuedDate": null,
          "verificationSource": "FL DOH MQA",
          "lastVerified": "2026-05-19T02:54:39.070Z",
          "disciplineActions": false
        }
      ],
      "statesSearched": 2,
      "statesWithLicense": 6,
      "lastFullScan": "2026-05-19T02:54:49.610Z"
    },
    "Lauren Dovin, RN": {
      "providerType": "RN",
      "licenses": [],
      "statesSearched": 2,
      "statesWithLicense": 0,
      "lastFullScan": "2026-03-02T15:31:22.306Z"
    },
    "Catherine Herrington, MD": {
      "providerType": "MD",
      "licenses": [
        {
          "state": "FL",
          "stateFullName": "Florida",
          "licenseNumber": "ME162177",
          "licenseType": "MD",
          "status": "Active",
          "expirationDate": null,
          "issuedDate": null,
          "verificationSource": "FL DOH MQA",
          "lastVerified": "2026-05-19T02:46:56.314Z",
          "disciplineActions": false
        },
        {
          "state": "FL",
          "stateFullName": "Florida",
          "licenseNumber": "PN633241",
          "licenseType": "RN",
          "status": "Unknown",
          "expirationDate": null,
          "issuedDate": null,
          "verificationSource": "FL DOH MQA",
          "lastVerified": "2026-05-19T02:46:56.314Z",
          "disciplineActions": false
        },
        {
          "state": "FL",
          "stateFullName": "Florida",
          "licenseNumber": null,
          "licenseType": "RN",
          "status": "Inactive",
          "expirationDate": null,
          "issuedDate": null,
          "verificationSource": "FL DOH MQA",
          "lastVerified": "2026-05-19T02:46:56.314Z",
          "disciplineActions": false
        }
      ],
      "statesSearched": 2,
      "statesWithLicense": 3,
      "lastFullScan": "2026-05-19T02:47:06.805Z"
    },
    "Doron Stember, MD": {
      "providerType": "MD",
      "licenses": [],
      "statesSearched": 2,
      "statesWithLicense": 0,
      "lastFullScan": "2026-05-19T02:47:26.332Z"
    },
    "Tzvi Doron, DO": {
      "providerType": "DO",
      "licenses": [
        {
          "state": "FL",
          "stateFullName": "Florida",
          "licenseNumber": "OS12294",
          "licenseType": "RN",
          "status": "Active",
          "expirationDate": null,
          "issuedDate": null,
          "verificationSource": "FL DOH MQA",
          "lastVerified": "2026-05-19T02:50:10.389Z",
          "disciplineActions": false
        },
        {
          "state": "FL",
          "stateFullName": "Florida",
          "licenseNumber": null,
          "licenseType": "RN",
          "status": "Inactive",
          "expirationDate": null,
          "issuedDate": null,
          "verificationSource": "FL DOH MQA",
          "lastVerified": "2026-05-19T02:50:10.389Z",
          "disciplineActions": false
        }
      ],
      "statesSearched": 2,
      "statesWithLicense": 2,
      "lastFullScan": "2026-05-19T02:50:21.045Z"
    },
    "Ashley Escoe, NP": {
      "providerType": "NP",
      "licenses": [
        {
          "state": "NH",
          "stateFullName": "New Hampshire",
          "licenseNumber": "084878",
          "licenseType": "APRN",
          "status": "Active",
          "expirationDate": null,
          "issuedDate": null,
          "verificationSource": "New Hampshire Board",
          "lastVerified": "2026-05-19T02:53:12.567Z",
          "disciplineActions": false
        }
      ],
      "statesSearched": 2,
      "statesWithLicense": 1,
      "lastFullScan": "2026-05-19T02:53:14.087Z"
    },
    "Emmanuel Sonaike, MD": {
      "providerType": "MD",
      "licenses": [],
      "statesSearched": 2,
      "statesWithLicense": 0,
      "lastFullScan": "2026-05-19T02:55:08.896Z"
    },
    "Naureen Majid Adam, MD": {
      "providerType": "MD",
      "licenses": [],
      "statesSearched": 2,
      "statesWithLicense": 0,
      "lastFullScan": "2026-05-19T02:55:28.491Z"
    },
    "Nicole Tahira Perrotte, MD": {
      "providerType": "MD",
      "licenses": [],
      "statesSearched": 2,
      "statesWithLicense": 0,
      "lastFullScan": "2026-05-19T02:55:48.340Z"
    }
  },
  "verificationStats": {
    "totalProviders": 37,
    "totalLicensesFound": 78,
    "activeLicenses": 42,
    "expiringWithin90Days": 0,
    "manualEntries": 0,
    "scrapedEntries": 78
  }
}